my_geometry_library/__init__.py
my_geometry_library-0.5.dist-info/METADATA
my_geometry_library-0.5.dist-info/WHEEL
my_geometry_library-0.5.dist-info/top_level.txt
my_geometry_library-0.5.dist-info/RECORD
