Metadata-Version: 2.1
Name: my-geometry-library
Version: 0.5
Summary: Python Library for simple Geometric Functions 
Author: Tarun Kumar
